apache_airflow_provider_magento/__init__.py
apache_airflow_provider_magento/hooks/__init__.py
apache_airflow_provider_magento/hooks/magento.py
apache_airflow_provider_magento/operators/__init__.py
apache_airflow_provider_magento/operators/asyncrest.py
apache_airflow_provider_magento/operators/dataimport.py
apache_airflow_provider_magento/operators/graphql.py
apache_airflow_provider_magento/operators/rest.py
apache_airflow_provider_magento/utils/__init__.py
apache_airflow_provider_magento/utils/paginate.py
example_dags/__init__.py
example_dags/adobe_commerce_import.py
example_dags/magento_async.py
example_dags/magento_bulk_create_customers.py
example_dags/magento_bulk_delete_products.py
example_dags/magento_customer_graphql.py
example_dags/magento_customer_order_rest_demo.py
example_dags/magento_guest_order_rest_demo.py
example_dags/magento_paginated.py
tests/hooks/__init__.py
tests/hooks/test_magento.py
apache_airflow_provider_magento-0.7.dist-info/LICENSE
apache_airflow_provider_magento-0.7.dist-info/METADATA
apache_airflow_provider_magento-0.7.dist-info/WHEEL
apache_airflow_provider_magento-0.7.dist-info/top_level.txt
apache_airflow_provider_magento-0.7.dist-info/RECORD
