Metadata-Version: 2.1
Name: apache-airflow-provider-magento
Version: 0.7
Summary: Custom provider for Magento 2 - Apache Airflow
Author-email: Sivakumar Koduru <sivajik34@gmail.com>
License: MIT
Project-URL: Homepage, https://github.com/sivajik34/magento-airflow
Keywords: airflow,magento,provider
Classifier: Programming Language :: Python :: 3
Classifier: License :: OSI Approved :: MIT License
Classifier: Operating System :: OS Independent
Requires-Python: >=3.8
License-File: LICENSE
Requires-Dist: apache-airflow >=2.8.0
Requires-Dist: requests-oauthlib
Requires-Dist: requests
